{
  "protocol_version" : "0.0.6",
  "configuration" : {
    "version" : "(6.10.0.106) (2019-12/77769615db1)",
    "tlc" : "normal",
    "sigsgev" : "altstack",
    "notifications" : "kqueue",
    "architecture" : "amd64",
    "disabled_features" : "none",
    "smallconfig" : "disabled",
    "bigarrays" : "disabled",
    "softdebug" : "enabled",
    "interpreter" : "enabled",
    "llvm_support" : "0",
    "suspend" : "hybrid"
  },
  "memory" : {
    "Resident Size" : "159113216",
    "Virtual Size" : "4613115904",
    "minor_gc_time" : "247439",
    "major_gc_time" : "0",
    "minor_gc_count" : "1",
    "major_gc_count" : "0",
    "major_gc_time_concurrent" : "0"
 },
  "threads" : [
 {
    "is_managed" : true,
    "offset_free_hash" : "0x1979963d15",
    "offset_rich_hash" : "0x197996403d",
    "crashed" : true,
    "native_thread_id" : "0x700007835000",
    "thread_info_addr" : "0x7ff83726ee00",
    "thread_name" : "Thread Pool Worker",
    "ctx" : {
      "IP" : "0x7fff6ae3e7fa",
      "SP" : "0x700007833648",
      "BP" : "0x700007833670"
  },
    "managed_frames" : [
  {
      "is_managed" : "false",
      "native_address" : "unregistered"
   }
,
  {
      "is_managed" : "true",
      "guid" : "D8DC2CE1-6D10-4014-8386-8046F78047E7",
      "token" : "0x00000",
      "native_offset" : "0x0",
      "filename" : "mscorlib.dll",
      "sizeofimage" : "0x474000",
      "timestamp" : "0xb483e3c0",
      "il_offset" : "0x0000c"
   }
,
  {
      "is_managed" : "true",
      "guid" : "D8DC2CE1-6D10-4014-8386-8046F78047E7",
      "token" : "0x6001f8c",
      "native_offset" : "0x0",
      "filename" : "mscorlib.dll",
      "sizeofimage" : "0x474000",
      "timestamp" : "0xb483e3c0",
      "il_offset" : "0x0001a"
   }
,
  {
      "is_managed" : "true",
      "guid" : "D8DC2CE1-6D10-4014-8386-8046F78047E7",
      "token" : "0x6001f32",
      "native_offset" : "0x0",
      "filename" : "mscorlib.dll",
      "sizeofimage" : "0x474000",
      "timestamp" : "0xb483e3c0",
      "il_offset" : "0x00028"
   }
,
  {
      "is_managed" : "true",
      "guid" : "D8DC2CE1-6D10-4014-8386-8046F78047E7",
      "token" : "0x6001f30",
      "native_offset" : "0x0",
      "filename" : "mscorlib.dll",
      "sizeofimage" : "0x474000",
      "timestamp" : "0xb483e3c0",
      "il_offset" : "0x00002"
   }
,
  {
      "is_managed" : "true",
      "guid" : "E5BBCD86-B476-47FC-970E-F00D99CDBAB3",
      "token" : "0x6000084",
      "native_offset" : "0x0",
      "filename" : "MonoDevelop.MSBuildBuilder.exe",
      "sizeofimage" : "0x18000",
      "timestamp" : "0xc077b0d4",
      "il_offset" : "0x000ae"
   }
,
  {
      "is_managed" : "true",
      "guid" : "E5BBCD86-B476-47FC-970E-F00D99CDBAB3",
      "token" : "0x6000083",
      "native_offset" : "0x0",
      "filename" : "MonoDevelop.MSBuildBuilder.exe",
      "sizeofimage" : "0x18000",
      "timestamp" : "0xc077b0d4",
      "il_offset" : "0x00001"
   }
,
  {
      "is_managed" : "true",
      "guid" : "E5BBCD86-B476-47FC-970E-F00D99CDBAB3",
      "token" : "0x600006a",
      "native_offset" : "0x0",
      "filename" : "MonoDevelop.MSBuildBuilder.exe",
      "sizeofimage" : "0x18000",
      "timestamp" : "0xc077b0d4",
      "il_offset" : "0x00048"
   }
,
  {
      "is_managed" : "true",
      "guid" : "E5BBCD86-B476-47FC-970E-F00D99CDBAB3",
      "token" : "0x60000a1",
      "native_offset" : "0x0",
      "filename" : "MonoDevelop.MSBuildBuilder.exe",
      "sizeofimage" : "0x18000",
      "timestamp" : "0xc077b0d4",
      "il_offset" : "0x00001"
   }
,
  {
      "is_managed" : "true",
      "guid" : "E5BBCD86-B476-47FC-970E-F00D99CDBAB3",
      "token" : "0x6000067",
      "native_offset" : "0x0",
      "filename" : "MonoDevelop.MSBuildBuilder.exe",
      "sizeofimage" : "0x18000",
      "timestamp" : "0xc077b0d4",
      "il_offset" : "0x00001"
   }
,
  {
      "is_managed" : "true",
      "guid" : "E5BBCD86-B476-47FC-970E-F00D99CDBAB3",
      "token" : "0x6000075",
      "native_offset" : "0x0",
      "filename" : "MonoDevelop.MSBuildBuilder.exe",
      "sizeofimage" : "0x18000",
      "timestamp" : "0xc077b0d4",
      "il_offset" : "0x00057"
   }
,
  {
      "is_managed" : "true",
      "guid" : "E5BBCD86-B476-47FC-970E-F00D99CDBAB3",
      "token" : "0x00000",
      "native_offset" : "0x0",
      "filename" : "MonoDevelop.MSBuildBuilder.exe",
      "sizeofimage" : "0x18000",
      "timestamp" : "0xc077b0d4",
      "il_offset" : "0x0002a"
   }
,
  {
      "is_managed" : "false",
      "native_address" : "unregistered"
   }
,
  {
      "is_managed" : "true",
      "guid" : "D8DC2CE1-6D10-4014-8386-8046F78047E7",
      "token" : "0x00000",
      "native_offset" : "0x0",
      "filename" : "mscorlib.dll",
      "sizeofimage" : "0x474000",
      "timestamp" : "0xb483e3c0",
      "il_offset" : "0x0000c"
   }
,
  {
      "is_managed" : "true",
      "guid" : "D8DC2CE1-6D10-4014-8386-8046F78047E7",
      "token" : "0x60048d1",
      "native_offset" : "0x0",
      "filename" : "mscorlib.dll",
      "sizeofimage" : "0x474000",
      "timestamp" : "0xb483e3c0",
      "il_offset" : "0x00000"
   }
,
  {
      "is_managed" : "true",
      "guid" : "E5BBCD86-B476-47FC-970E-F00D99CDBAB3",
      "token" : "0x6000039",
      "native_offset" : "0x0",
      "filename" : "MonoDevelop.MSBuildBuilder.exe",
      "sizeofimage" : "0x18000",
      "timestamp" : "0xc077b0d4",
      "il_offset" : "0x00019"
   }
,
  {
      "is_managed" : "true",
      "guid" : "E5BBCD86-B476-47FC-970E-F00D99CDBAB3",
      "token" : "0x6000169",
      "native_offset" : "0x0",
      "filename" : "MonoDevelop.MSBuildBuilder.exe",
      "sizeofimage" : "0x18000",
      "timestamp" : "0xc077b0d4",
      "il_offset" : "0x00029"
   }
,
  {
      "is_managed" : "true",
      "guid" : "E5BBCD86-B476-47FC-970E-F00D99CDBAB3",
      "token" : "0x6000184",
      "native_offset" : "0x0",
      "filename" : "MonoDevelop.MSBuildBuilder.exe",
      "sizeofimage" : "0x18000",
      "timestamp" : "0xc077b0d4",
      "il_offset" : "0x00001"
   }
,
  {
      "is_managed" : "true",
      "guid" : "D8DC2CE1-6D10-4014-8386-8046F78047E7",
      "token" : "0x6001ece",
      "native_offset" : "0x0",
      "filename" : "mscorlib.dll",
      "sizeofimage" : "0x474000",
      "timestamp" : "0xb483e3c0",
      "il_offset" : "0x00071"
   }
,
  {
      "is_managed" : "true",
      "guid" : "D8DC2CE1-6D10-4014-8386-8046F78047E7",
      "token" : "0x6001ecc",
      "native_offset" : "0x0",
      "filename" : "mscorlib.dll",
      "sizeofimage" : "0x474000",
      "timestamp" : "0xb483e3c0",
      "il_offset" : "0x00000"
   }
,
  {
      "is_managed" : "true",
      "guid" : "D8DC2CE1-6D10-4014-8386-8046F78047E7",
      "token" : "0x6001fd9",
      "native_offset" : "0x0",
      "filename" : "mscorlib.dll",
      "sizeofimage" : "0x474000",
      "timestamp" : "0xb483e3c0",
      "il_offset" : "0x00074"
   }
,
  {
      "is_managed" : "true",
      "guid" : "D8DC2CE1-6D10-4014-8386-8046F78047E7",
      "token" : "0x6001fee",
      "native_offset" : "0x0",
      "filename" : "mscorlib.dll",
      "sizeofimage" : "0x474000",
      "timestamp" : "0xb483e3c0",
      "il_offset" : "0x00000"
   }
,
  {
      "is_managed" : "true",
      "guid" : "D8DC2CE1-6D10-4014-8386-8046F78047E7",
      "token" : "0x00000",
      "native_offset" : "0x0",
      "filename" : "mscorlib.dll",
      "sizeofimage" : "0x474000",
      "timestamp" : "0xb483e3c0",
      "il_offset" : "0x0002a"
   }

  ],
  "unmanaged_frames" : [
 {
    "is_managed" : "false",
    "native_address" : "0x10c705346",
    "native_offset" : "0x00000"
  }
,
 {
    "is_managed" : "false",
    "native_address" : "0x10c89faa5",
    "native_offset" : "0x00000"
  }
,
 {
    "is_managed" : "false",
    "native_address" : "0x10c8a011a",
    "native_offset" : "0x00000"
  }
,
 {
    "is_managed" : "false",
    "native_address" : "0x10c771da7",
    "native_offset" : "0x00000"
  }
,
 {
    "is_managed" : "false",
    "native_address" : "0x10c709fb5",
    "native_offset" : "0x00000"
  }
,
 {
    "is_managed" : "false",
    "native_address" : "0x10c77109f",
    "native_offset" : "0x00000"
  }
,
 {
    "is_managed" : "false",
    "native_address" : "0x7fff6aef042d",
    "native_offset" : "0x00000"
  }
,
 {
    "is_managed" : "false",
    "native_address" : "unregistered"
  }
,
 {
    "is_managed" : "false",
    "native_address" : "0x7fff6adc5a1c",
    "native_offset" : "0x00000"
  }
,
 {
    "is_managed" : "false",
    "native_address" : "0x10c96f397",
    "native_offset" : "0x00000"
  }
,
 {
    "is_managed" : "false",
    "native_address" : "0x10c95027f",
    "native_offset" : "0x00000"
  }
,
 {
    "is_managed" : "false",
    "native_address" : "0x10c96f71e",
    "native_offset" : "0x00000"
  }
,
 {
    "is_managed" : "false",
    "native_address" : "0x10c96f89f",
    "native_offset" : "0x00000"
  }
,
 {
    "is_managed" : "false",
    "native_address" : "0x10c80c059",
    "native_offset" : "0x00000"
  }
,
 {
    "is_managed" : "false",
    "native_address" : "0x10c80c5f2",
    "native_offset" : "0x00000"
  }
,
 {
    "is_managed" : "false",
    "native_address" : "0x10c95d6d1",
    "native_offset" : "0x00000"
  }
,
 {
    "is_managed" : "false",
    "native_address" : "0x10c95da70",
    "native_offset" : "0x00000"
  }
,
 {
    "is_managed" : "false",
    "native_address" : "0x10c80e706",
    "native_offset" : "0x00000"
  }
,
 {
    "is_managed" : "false",
    "native_address" : "0x10c832ab4",
    "native_offset" : "0x00000"
  }
,
 {
    "is_managed" : "true",
    "guid" : "D8DC2CE1-6D10-4014-8386-8046F78047E7",
    "token" : "0x00000",
    "native_offset" : "0x0",
    "filename" : "mscorlib.dll",
    "sizeofimage" : "0x474000",
    "timestamp" : "0xb483e3c0",
    "il_offset" : "0x00000"
  }
,
 {
    "is_managed" : "true",
    "guid" : "D8DC2CE1-6D10-4014-8386-8046F78047E7",
    "token" : "0x6001f8c",
    "native_offset" : "0x0",
    "filename" : "mscorlib.dll",
    "sizeofimage" : "0x474000",
    "timestamp" : "0xb483e3c0",
    "il_offset" : "0x00000"
  }
,
 {
    "is_managed" : "true",
    "guid" : "E5BBCD86-B476-47FC-970E-F00D99CDBAB3",
    "token" : "0x6000083",
    "native_offset" : "0x0",
    "filename" : "MonoDevelop.MSBuildBuilder.exe",
    "sizeofimage" : "0x18000",
    "timestamp" : "0xc077b0d4",
    "il_offset" : "0x00000"
  }
,
 {
    "is_managed" : "true",
    "guid" : "E5BBCD86-B476-47FC-970E-F00D99CDBAB3",
    "token" : "0x600006a",
    "native_offset" : "0x0",
    "filename" : "MonoDevelop.MSBuildBuilder.exe",
    "sizeofimage" : "0x18000",
    "timestamp" : "0xc077b0d4",
    "il_offset" : "0x00000"
  }
,
 {
    "is_managed" : "true",
    "guid" : "E5BBCD86-B476-47FC-970E-F00D99CDBAB3",
    "token" : "0x60000a1",
    "native_offset" : "0x0",
    "filename" : "MonoDevelop.MSBuildBuilder.exe",
    "sizeofimage" : "0x18000",
    "timestamp" : "0xc077b0d4",
    "il_offset" : "0x00000"
  }
,
 {
    "is_managed" : "true",
    "guid" : "E5BBCD86-B476-47FC-970E-F00D99CDBAB3",
    "token" : "0x6000067",
    "native_offset" : "0x0",
    "filename" : "MonoDevelop.MSBuildBuilder.exe",
    "sizeofimage" : "0x18000",
    "timestamp" : "0xc077b0d4",
    "il_offset" : "0x00000"
  }
,
 {
    "is_managed" : "true",
    "guid" : "E5BBCD86-B476-47FC-970E-F00D99CDBAB3",
    "token" : "0x6000075",
    "native_offset" : "0x0",
    "filename" : "MonoDevelop.MSBuildBuilder.exe",
    "sizeofimage" : "0x18000",
    "timestamp" : "0xc077b0d4",
    "il_offset" : "0x00000"
  }
,
 {
    "is_managed" : "true",
    "guid" : "E5BBCD86-B476-47FC-970E-F00D99CDBAB3",
    "token" : "0x00000",
    "native_offset" : "0x0",
    "filename" : "MonoDevelop.MSBuildBuilder.exe",
    "sizeofimage" : "0x18000",
    "timestamp" : "0xc077b0d4",
    "il_offset" : "0x00000"
  }
,
 {
    "is_managed" : "false",
    "native_address" : "0x10c667ae2",
    "native_offset" : "0x00000"
  }
,
 {
    "is_managed" : "false",
    "native_address" : "0x10c875967",
    "native_offset" : "0x00000"
  }
,
 {
    "is_managed" : "false",
    "native_address" : "0x10c87e409",
    "native_offset" : "0x00000"
  }
,
 {
    "is_managed" : "false",
    "native_address" : "0x10c81638d",
    "native_offset" : "0x00000"
  }
,
 {
    "is_managed" : "false",
    "native_address" : "0x10c82a027",
    "native_offset" : "0x00000"
  }
,
 {
    "is_managed" : "true",
    "guid" : "D8DC2CE1-6D10-4014-8386-8046F78047E7",
    "token" : "0x00000",
    "native_offset" : "0x0",
    "filename" : "mscorlib.dll",
    "sizeofimage" : "0x474000",
    "timestamp" : "0xb483e3c0",
    "il_offset" : "0x00000"
  }
,
 {
    "is_managed" : "true",
    "guid" : "(null)",
    "token" : "0x00000",
    "native_offset" : "0x0",
    "filename" : "(null)",
    "sizeofimage" : "0x0",
    "timestamp" : "0x0",
    "il_offset" : "0x00000"
  }
,
 {
    "is_managed" : "true",
    "guid" : "D8DC2CE1-6D10-4014-8386-8046F78047E7",
    "token" : "0x60048d1",
    "native_offset" : "0x0",
    "filename" : "mscorlib.dll",
    "sizeofimage" : "0x474000",
    "timestamp" : "0xb483e3c0",
    "il_offset" : "0x00000"
  }
,
 {
    "is_managed" : "true",
    "guid" : "E5BBCD86-B476-47FC-970E-F00D99CDBAB3",
    "token" : "0x6000169",
    "native_offset" : "0x0",
    "filename" : "MonoDevelop.MSBuildBuilder.exe",
    "sizeofimage" : "0x18000",
    "timestamp" : "0xc077b0d4",
    "il_offset" : "0x00000"
  }
,
 {
    "is_managed" : "true",
    "guid" : "E5BBCD86-B476-47FC-970E-F00D99CDBAB3",
    "token" : "0x6000184",
    "native_offset" : "0x0",
    "filename" : "MonoDevelop.MSBuildBuilder.exe",
    "sizeofimage" : "0x18000",
    "timestamp" : "0xc077b0d4",
    "il_offset" : "0x00000"
  }
,
 {
    "is_managed" : "true",
    "guid" : "(null)",
    "token" : "0x00000",
    "native_offset" : "0x0",
    "filename" : "(null)",
    "sizeofimage" : "0x0",
    "timestamp" : "0x0",
    "il_offset" : "0x00000"
  }
,
 {
    "is_managed" : "true",
    "guid" : "D8DC2CE1-6D10-4014-8386-8046F78047E7",
    "token" : "0x6001ecc",
    "native_offset" : "0x0",
    "filename" : "mscorlib.dll",
    "sizeofimage" : "0x474000",
    "timestamp" : "0xb483e3c0",
    "il_offset" : "0x00000"
  }
,
 {
    "is_managed" : "true",
    "guid" : "D8DC2CE1-6D10-4014-8386-8046F78047E7",
    "token" : "0x6001fee",
    "native_offset" : "0x0",
    "filename" : "mscorlib.dll",
    "sizeofimage" : "0x474000",
    "timestamp" : "0xb483e3c0",
    "il_offset" : "0x00000"
  }
,
 {
    "is_managed" : "false",
    "native_address" : "0x10c667ae2",
    "native_offset" : "0x00000"
  }
,
 {
    "is_managed" : "false",
    "native_address" : "0x10c877342",
    "native_offset" : "0x00000"
  }
,
 {
    "is_managed" : "false",
    "native_address" : "0x10c8a31c7",
    "native_offset" : "0x00000"
  }
,
 {
    "is_managed" : "false",
    "native_address" : "0x10c7d6f88",
    "native_offset" : "0x00000"
  }
,
 {
    "is_managed" : "false",
    "native_address" : "0x10c8a06ed",
    "native_offset" : "0x00000"
  }
,
 {
    "is_managed" : "false",
    "native_address" : "0x7fff6aefbe65",
    "native_offset" : "0x00000"
  }
,
 {
    "is_managed" : "false",
    "native_address" : "0x7fff6aef783b",
    "native_offset" : "0x00000"
  }

 ]
},
{
  "is_managed" : false,
  "offset_free_hash" : "0x0",
  "offset_rich_hash" : "0x0",
  "crashed" : false,
  "native_thread_id" : "0x1140a9dc0",
  "thread_info_addr" : "0x7ff83700c000",
  "thread_name" : "tid_307",
  "ctx" : {
    "IP" : "0x7fff6ae3ace6",
    "SP" : "0x7ffee35aac78",
    "BP" : "0x7ffee35aad10"
 },
  "unmanaged_frames" : [
 {
    "is_managed" : "false",
    "native_address" : "0x10c705346",
    "native_offset" : "0x00000"
  }
,
 {
    "is_managed" : "false",
    "native_address" : "0x10c89faa5",
    "native_offset" : "0x00000"
  }
,
 {
    "is_managed" : "false",
    "native_address" : "0x10c89f7d7",
    "native_offset" : "0x00000"
  }
,
 {
    "is_managed" : "false",
    "native_address" : "0x10c770ce0",
    "native_offset" : "0x00000"
  }
,
 {
    "is_managed" : "false",
    "native_address" : "0x7fff6aef042d",
    "native_offset" : "0x00000"
  }
,
 {
    "is_managed" : "false",
    "native_address" : "0x7ffee35aa968",
    "native_offset" : "0x00000"
  }
,
 {
    "is_managed" : "false",
    "native_address" : "0x10c94c430",
    "native_offset" : "0x00000"
  }
,
 {
    "is_managed" : "false",
    "native_address" : "0x10c964401",
    "native_offset" : "0x00000"
  }
,
 {
    "is_managed" : "false",
    "native_address" : "0x10c89c9e4",
    "native_offset" : "0x00000"
  }
,
 {
    "is_managed" : "false",
    "native_address" : "0x10c89c7ea",
    "native_offset" : "0x00000"
  }
,
 {
    "is_managed" : "false",
    "native_address" : "0x10c6cb30a",
    "native_offset" : "0x00000"
  }
,
 {
    "is_managed" : "false",
    "native_address" : "0x10c656e49",
    "native_offset" : "0x00000"
  }
,
 {
    "is_managed" : "false",
    "native_address" : "0x7fff6acf77fd",
    "native_offset" : "0x00000"
  }

 ]
},
{
  "is_managed" : false,
  "offset_free_hash" : "0xb38e38cc",
  "offset_rich_hash" : "0xb38e38cc",
  "crashed" : false,
  "native_thread_id" : "0x700007126000",
  "thread_info_addr" : "0x7ff839008e00",
  "thread_name" : "Finalizer",
  "ctx" : {
    "IP" : "0x7fff6ae38296",
    "SP" : "0x700007125eb8",
    "BP" : "0x700007125f00"
 },
  "unmanaged_frames" : [
 {
    "is_managed" : "false",
    "native_address" : "0x10c705346",
    "native_offset" : "0x00000"
  }
,
 {
    "is_managed" : "false",
    "native_address" : "0x10c89faa5",
    "native_offset" : "0x00000"
  }
,
 {
    "is_managed" : "false",
    "native_address" : "0x10c89f7d7",
    "native_offset" : "0x00000"
  }
,
 {
    "is_managed" : "false",
    "native_address" : "0x10c770ce0",
    "native_offset" : "0x00000"
  }
,
 {
    "is_managed" : "false",
    "native_address" : "0x7fff6aef042d",
    "native_offset" : "0x00000"
  }
,
 {
    "is_managed" : "true",
    "guid" : "D8DC2CE1-6D10-4014-8386-8046F78047E7",
    "token" : "0x6001467",
    "native_offset" : "0x0",
    "filename" : "mscorlib.dll",
    "sizeofimage" : "0x474000",
    "timestamp" : "0xb483e3c0",
    "il_offset" : "0x00000"
  }
,
 {
    "is_managed" : "false",
    "native_address" : "0x10c8a06ed",
    "native_offset" : "0x00000"
  }
,
 {
    "is_managed" : "false",
    "native_address" : "0x7fff6aefbe65",
    "native_offset" : "0x00000"
  }
,
 {
    "is_managed" : "false",
    "native_address" : "0x7fff6aef783b",
    "native_offset" : "0x00000"
  }

 ]
}
]
}